ChromePasswordsStealer.py
LICENSE.txt
MANIFEST.in
README.md
compile.bat
compile_onedir.spec
compile_onefile.spec
file_version_info.txt
requirements.txt
setup.cfg
setup.py
ChromePasswordsStealer.egg-info/PKG-INFO
ChromePasswordsStealer.egg-info/SOURCES.txt
ChromePasswordsStealer.egg-info/dependency_links.txt
ChromePasswordsStealer.egg-info/entry_points.txt
ChromePasswordsStealer.egg-info/requires.txt
ChromePasswordsStealer.egg-info/top_level.txt