Metadata-Version: 2.1
Name: ChromePasswordsStealer
Version: 1.0.1
Summary: This module steals chrome passwords on Windows.
Home-page: https://github.com/mauricelambert/ChromePasswordsStealer
Author: Maurice Lambert
Author-email: mauricelambert434@gmail.com
Maintainer: Maurice Lambert
Maintainer-email: mauricelambert434@gmail.com
License: GPL-3.0 License
Project-URL: Documentation, https://mauricelambert.github.io/info/python/security/ChromePasswordsStealer.html
Project-URL: Executable, https://mauricelambert.github.io/info/python/security/ChromePasswordsStealer.pyz
Keywords: Chrome,Google,Passwords,Decrypt,Steal,Recovery,Security
Platform: Windows
Classifier: Programming Language :: Python
Classifier: Development Status :: 5 - Production/Stable
Classifier: Environment :: Console
Classifier: Natural Language :: English
Classifier: Topic :: Security
Classifier: Natural Language :: English
Classifier: Programming Language :: Python :: 3.9
Classifier: Operating System :: Microsoft :: Windows
Requires-Python: >=3.8
License-File: LICENSE.txt
